rdagent/app/cli.py
rdagent/app/CI/README.md
rdagent/app/CI/ci.ipynb
rdagent/app/CI/prompts.yaml
rdagent/app/CI/run.py
rdagent/app/benchmark/factor/analysis.py
rdagent/app/benchmark/factor/eval.py
rdagent/app/benchmark/model/README.md
rdagent/app/benchmark/model/eval.py
rdagent/app/data_science/conf.py
rdagent/app/data_science/debug.py
rdagent/app/data_science/loop.py
rdagent/app/general_model/general_model.py
rdagent/app/kaggle/conf.py
rdagent/app/kaggle/loop.py
rdagent/app/qlib_rd_loop/conf.py
rdagent/app/qlib_rd_loop/factor.py
rdagent/app/qlib_rd_loop/factor_from_report.py
rdagent/app/qlib_rd_loop/model.py
rdagent/app/qlib_rd_loop/prompts.yaml
rdagent/app/qlib_rd_loop/quant.py
rdagent/app/utils/ape.py
rdagent/app/utils/health_check.py
rdagent/app/utils/info.py
rdagent/app/utils/prompts.yaml
rdagent/components/benchmark/conf.py
rdagent/components/benchmark/eval_method.py
rdagent/components/benchmark/example.json
rdagent/components/coder/CoSTEER/__init__.py
rdagent/components/coder/CoSTEER/config.py
rdagent/components/coder/CoSTEER/evaluators.py
rdagent/components/coder/CoSTEER/evolvable_subjects.py
rdagent/components/coder/CoSTEER/evolving_strategy.py
rdagent/components/coder/CoSTEER/knowledge_management.py
rdagent/components/coder/CoSTEER/prompts.yaml
rdagent/components/coder/CoSTEER/task.py
rdagent/components/coder/data_science/conf.py
rdagent/components/coder/data_science/utils.py
rdagent/components/coder/data_science/ensemble/__init__.py
rdagent/components/coder/data_science/ensemble/conf.py
rdagent/components/coder/data_science/ensemble/eval.py
rdagent/components/coder/data_science/ensemble/exp.py
rdagent/components/coder/data_science/ensemble/prompts.yaml
rdagent/components/coder/data_science/ensemble/test.py
rdagent/components/coder/data_science/ensemble/eval_tests/ensemble_test.txt
rdagent/components/coder/data_science/feature/__init__.py
rdagent/components/coder/data_science/feature/eval.py
rdagent/components/coder/data_science/feature/exp.py
rdagent-0.7.0.dist-info/licenses/LICENSE
rdagent-0.7.0.dist-info/METADATA
rdagent-0.7.0.dist-info/WHEEL
rdagent-0.7.0.dist-info/entry_points.txt
rdagent-0.7.0.dist-info/top_level.txt
rdagent-0.7.0.dist-info/RECORD
