Metadata-Version: 2.4
Name: rdagent
Version: 0.7.0
Summary: Research & Development Agent
Author-email: MSRA-MIIC <xuyang1@microsoft.com>
Project-URL: homepage, https://github.com/microsoft/RD-Agent/
Project-URL: issue, https://github.com/microsoft/RD-Agent/issues
Keywords: Autonomous Agents,Large Language Models,Research and Development
Classifier: Development Status :: 3 - Alpha
Classifier: License :: OSI Approved :: MIT License
Classifier: Operating System :: OS Independent
Classifier: Programming Language :: Python :: 3.10
Classifier: Programming Language :: Python :: 3.11
Requires-Python: >=3.10
License-File: LICENSE
Requires-Dist: pydantic-settings
Requires-Dist: python-Levenshtein
Requires-Dist: scikit-learn
Requires-Dist: filelock
Requires-Dist: loguru
Requires-Dist: fire
Requires-Dist: fuzzywuzzy
Requires-Dist: openai
Requires-Dist: litellm==1.72.4
Requires-Dist: azure.identity
Requires-Dist: pyarrow
Requires-Dist: rich
Requires-Dist: tqdm
Requires-Dist: typer
Requires-Dist: numpy
Requires-Dist: pandas
Requires-Dist: pandarallel
Requires-Dist: matplotlib
Requires-Dist: langchain
Requires-Dist: langchain-community
Requires-Dist: tiktoken
Requires-Dist: pymupdf
Requires-Dist: pypdf
Requires-Dist: azure-ai-formrecognizer
Requires-Dist: tables
Requires-Dist: tree-sitter-python
Requires-Dist: tree-sitter
Requires-Dist: python-dotenv
Requires-Dist: docker
Requires-Dist: streamlit
Requires-Dist: plotly
Requires-Dist: st-theme
Requires-Dist: randomname
Requires-Dist: flask
Requires-Dist: flask-cors
Requires-Dist: networkx
Requires-Dist: selenium
Requires-Dist: kaggle
Requires-Dist: nbformat
Requires-Dist: setuptools-scm
Requires-Dist: seaborn
Requires-Dist: azure.ai.inference
Requires-Dist: humanize
Requires-Dist: genson
Requires-Dist: mlflow
Requires-Dist: azureml-mlflow
Requires-Dist: types-pytz
Provides-Extra: docs
Requires-Dist: autodoc-pydantic; extra == "docs"
Requires-Dist: coverage; extra == "docs"
Requires-Dist: furo; extra == "docs"
Requires-Dist: git-changelog; extra == "docs"
Requires-Dist: mypy[reports]; extra == "docs"
Requires-Dist: myst-parser; extra == "docs"
Requires-Dist: pytest; extra == "docs"
Requires-Dist: Sphinx; extra == "docs"
Requires-Dist: sphinx-autobuild; extra == "docs"
Requires-Dist: sphinx-click; extra == "docs"
Requires-Dist: sphinx-togglebutton; extra == "docs"
Requires-Dist: sphinx_rtd_theme; extra == "docs"
Requires-Dist: snowballstemmer<3.0; extra == "docs"
Provides-Extra: lint
Requires-Dist: black; extra == "lint"
Requires-Dist: isort; extra == "lint"
Requires-Dist: mypy; extra == "lint"
Requires-Dist: ruff; extra == "lint"
Requires-Dist: toml-sort; extra == "lint"
Requires-Dist: types-PyYAML; extra == "lint"
Requires-Dist: types-psutil; extra == "lint"
Requires-Dist: types-tqdm; extra == "lint"
Provides-Extra: package
Requires-Dist: build; extra == "package"
Requires-Dist: setuptools-scm; extra == "package"
Requires-Dist: twine; extra == "package"
Requires-Dist: wheel; extra == "package"
Provides-Extra: test
Requires-Dist: coverage; extra == "test"
Requires-Dist: pytest; extra == "test"
Dynamic: license-file
